rods/BeamColumn.py
rods/Example_Code.py
rods/ModeShape.py
rods/Weakened.py
rods/__init__.py
rods/__main__.py
rods/csbdi.py
rods/stable.py
rods/corot/Lees_frame_2d_elastic.py
rods/corot/Lees_frame_2d_elastoplastic.py
rods/corot/Lees_frame_3d_elastic.py
rods/corot/Lees_frame_3d_elastic_rotated.py
rods/corot/Lees_frame_3d_elastoplastic.py
rods/corot/Lees_frame_3d_elastoplastic_rotated.py
rods/corot/cantilever_beam_2d_elastic.py
rods/corot/cantilever_beam_2d_elastoplastic.py
rods/corot/cantilever_beam_3d_elastic.py
rods/corot/cantilever_beam_3d_elastoplastic.py
rods/corot/cyclic_loading.py
rods/corot/toggle_frame_2d_elastic.py
rods/corot/toggle_frame_2d_elastoplastic.py
rods/corot/toggle_frame_3d_elastic.py
rods/corot/toggle_frame_3d_elastoplastic.py
rods/denavit/BeamColumn.py
rods/denavit/CBDI.py
rods/denavit/Example_Code.py
rods/denavit/ModeShape.py
rods/denavit/Prismatic.py
rods/denavit/Tapered.py
rods/denavit/Weakened.py
rods/denavit/__init__.py
rods/euler/Timoshenko/TimoshenkoFormulas.py
rods/euler/euler/LoadFormulas.py
rods/exact/_projection.py
rods/exact/_structures.py
rods/exact/cmp_elements.py
rods/exact/contact.py
rods/exact/domain.py
rods/exact/elements.py
rods/exact/errors.py
rods/exact/interpolation.py
rods/exact/mathematics.py
rods/exact/mesh.py
rods/exact/new_element.py
rods/exact/newton_raphson.py
rods/exact/postprocessing.py
rods/exact/section.py
rods/exact/system.py
rods/exact/tests/cantilever.py
rods/exact/tests/cantilever2.py
rods/exact/tests/frame.py
rods/exact/tests/patch.py
rods/exact/tests/twist.py
rods-0.0.3.dist-info/METADATA
rods-0.0.3.dist-info/WHEEL
rods-0.0.3.dist-info/entry_points.txt
rods-0.0.3.dist-info/top_level.txt
rods-0.0.3.dist-info/RECORD
